languageFreeAcq/AcqSystem.py
languageFreeAcq/Acquisition.py
languageFreeAcq/Common.py
languageFreeAcq/CspScopesRelations.py
languageFreeAcq/MaxSatAcq.py
languageFreeAcq/MaxSatOrTools.py
languageFreeAcq/__init__.py
languagefreeacq-0.0.7.dist-info/licenses/LICENCE
languagefreeacq-0.0.7.dist-info/METADATA
languagefreeacq-0.0.7.dist-info/WHEEL
languagefreeacq-0.0.7.dist-info/top_level.txt
languagefreeacq-0.0.7.dist-info/RECORD
