Metadata-Version: 2.4
Name: languageFreeAcq
Version: 0.0.7
Summary: A small package for the language free acquisition of a constraint network
Author-email: Areski Himeur <areski.himeur@lirmm.fr>
Project-URL: Homepage, https://github.com/Hareski/language-free-acq
Project-URL: Issues, https://github.com/Hareski/language-free-acq/issues
Classifier: Programming Language :: Python :: 3
Classifier: License :: OSI Approved :: Academic Free License (AFL)
Classifier: Operating System :: OS Independent
Requires-Python: >=3.8
License-File: LICENCE
Requires-Dist: ortools>=9.10.4067
Requires-Dist: tqdm>=4.66.3
Dynamic: license-file
